<?xml version="1.0" encoding="utf-8" ?>
<dwsync>
<file name="fontawesome-webfont.eot" server="ssh.strato.de/rent-tinyhouse.de/" local="132598688170000000" remote="132598688170000000" Dst="2" />
<file name="fontawesome-webfont.svg" server="ssh.strato.de/rent-tinyhouse.de/" local="132598688180000000" remote="132598688180000000" Dst="2" />
<file name="fontawesome-webfont.ttf" server="ssh.strato.de/rent-tinyhouse.de/" local="132598688180000000" remote="132598688180000000" Dst="2" />
<file name="fontawesome-webfont.woff" server="ssh.strato.de/rent-tinyhouse.de/" local="132598688180000000" remote="132598688180000000" Dst="2" />
<file name="fontawesome-webfont.woff2" server="ssh.strato.de/rent-tinyhouse.de/" local="132598688180000000" remote="132598688180000000" Dst="2" />
<file name="FontAwesome.otf" server="ssh.strato.de/rent-tinyhouse.de/" local="132598688190000000" remote="132598688190000000" Dst="2" />
<file name="fontawesome-webfont.eot" server="mrimbiss.com/httpdocs/" local="132598688170000000" remote="132987242630000000" Dst="2" />
<file name="fontawesome-webfont.svg" server="mrimbiss.com/httpdocs/" local="132598688180000000" remote="132987242630000000" Dst="2" />
<file name="fontawesome-webfont.ttf" server="mrimbiss.com/httpdocs/" local="132598688180000000" remote="132987242640000000" Dst="2" />
<file name="fontawesome-webfont.woff" server="mrimbiss.com/httpdocs/" local="132598688180000000" remote="132987242640000000" Dst="2" />
<file name="fontawesome-webfont.woff2" server="mrimbiss.com/httpdocs/" local="132598688180000000" remote="132987242640000000" Dst="2" />
<file name="FontAwesome.otf" server="mrimbiss.com/httpdocs/" local="132598688190000000" remote="132987242640000000" Dst="2" />
<file name="fontawesome-webfont.eot" server="weseeon.com/httpdocs/" local="132598688170000000" remote="133007941370000000" Dst="2" />
<file name="fontawesome-webfont.svg" server="weseeon.com/httpdocs/" local="132598688180000000" remote="133007941370000000" Dst="2" />
<file name="fontawesome-webfont.ttf" server="weseeon.com/httpdocs/" local="132598688180000000" remote="133007941370000000" Dst="2" />
<file name="fontawesome-webfont.woff" server="weseeon.com/httpdocs/" local="132598688180000000" remote="133007941370000000" Dst="2" />
<file name="fontawesome-webfont.woff2" server="weseeon.com/httpdocs/" local="132598688180000000" remote="133007941370000000" Dst="2" />
<file name="FontAwesome.otf" server="weseeon.com/httpdocs/" local="132598688190000000" remote="133007941380000000" Dst="2" />
</dwsync>